lumtina/__init__.py
lumtina/ascii_converter.py
lumtina/browser.py
lumtina/changelogs.py
lumtina/color.py
lumtina/console.py
lumtina/datetime_utils.py
lumtina/file_handler.py
lumtina/host.py
lumtina/logger.py
lumtina/math_update.py
lumtina/network_utils.py
lumtina/password_generator.py
lumtina/timer.py
lumtina/url.py
lumtina-0.2.8.dist-info/METADATA
lumtina-0.2.8.dist-info/WHEEL
lumtina-0.2.8.dist-info/top_level.txt
lumtina-0.2.8.dist-info/RECORD
