Metadata-Version: 2.1
Name: lumtina
Version: 0.2.8
Summary: Lumtina is a Python package for various utilities.
Home-page: https://github.com/sonosimooo/Lumtina
Author: Simo
Author-email: cardellasimone10@gmail.com
Classifier: Programming Language :: Python :: 3
Classifier: License :: OSI Approved :: MIT License
Classifier: Operating System :: OS Independent
Requires-Python: >=3.6
Requires-Dist: colorama
